brainsprite/__init__.py
brainsprite/brainsprite.py
brainsprite/setup.py
brainsprite/data/__init__.py
brainsprite/data/html/__init__.py
brainsprite/data/html/brainsprite_template.html
brainsprite/data/html/brainsprite_template_base64.html
brainsprite/data/html/viewer_template.html
brainsprite/data/js/__init__.py
brainsprite/data/js/brainsprite.min.js
brainsprite/data/js/brainsprite_template.js
brainsprite/data/js/jquery.min.js
brainsprite/tests/__init__.py
brainsprite/tests/test_brainsprite.py
brainsprite-0.14.2.dist-info/LICENSE
brainsprite-0.14.2.dist-info/METADATA
brainsprite-0.14.2.dist-info/WHEEL
brainsprite-0.14.2.dist-info/top_level.txt
brainsprite-0.14.2.dist-info/RECORD
