Metadata-Version: 2.1
Name: brainsprite
Version: 0.14.2
Summary: Python API for the brainsprite MRI brain viewer
Home-page: https://brainsprite.github.io
Maintainer: Pierre Bellec
Maintainer-email: pierre.bellec@gmail.com
License: UNKNOWN
Project-URL: Bug Reports, https://github.com/brainsprite/brainsprite/issues
Project-URL: Funding, https://ccna-ccnv.ca/
Project-URL: Source, https://github.com/brainsprite/brainsprite/
Platform: UNKNOWN
Classifier: Development Status :: 3 - Alpha
Classifier: Intended Audience :: Developers
Classifier: Topic :: Software Development :: Build Tools
Classifier: License :: OSI Approved :: MIT License
Classifier: Programming Language :: Python :: 3.5
Classifier: Programming Language :: Python :: 3.6
Classifier: Programming Language :: Python :: 3.7
Classifier: Programming Language :: Python :: 3.8
Requires-Python: >=3.5
Requires-Dist: numpy
Requires-Dist: matplotlib
Requires-Dist: sklearn
Requires-Dist: nilearn
Requires-Dist: tempita
